<?xml version="1.0" encoding="UTF-8"?>
<annotations xmlns="http://himeros.eu/euporia">
    <div n="1.0">* 1.0.1 Criseida: #name Criseida is_daughter_of Crise.
</div>
    <div n="1.1">* 1.1.1 Achille: #person Achille is_son_of Pelèo.
* 1.1.2 Pelèo: #person
* 1.1.8 Cani: #animal this has_lemma cane.
* 1.1.8 Corvi: #animal this has_lemma corvo.
</div>
    <div n="1.2">* 1.2.1 Dio: #god this denotes Zeus.
</div>
<div n="1.3">* 1.3.1 Febo: #god
</div><div n="1.4">* 1.4.3 Troia: #city
</div></annotations>